odoo10_addon_crm_sale_marketing-10.0.1.0.0-py2.7-nspkg.pth
odoo/addons/crm_sale_marketing/README.rst
odoo/addons/crm_sale_marketing/__init__.py
odoo/addons/crm_sale_marketing/__manifest__.py
odoo/addons/crm_sale_marketing/static/description/icon.png
odoo/addons/crm_sale_marketing/views/crm_sale_marketing.xml
odoo10_addon_crm_sale_marketing-10.0.1.0.0.dist-info/DESCRIPTION.rst
odoo10_addon_crm_sale_marketing-10.0.1.0.0.dist-info/METADATA
odoo10_addon_crm_sale_marketing-10.0.1.0.0.dist-info/RECORD
odoo10_addon_crm_sale_marketing-10.0.1.0.0.dist-info/WHEEL
odoo10_addon_crm_sale_marketing-10.0.1.0.0.dist-info/metadata.json
odoo10_addon_crm_sale_marketing-10.0.1.0.0.dist-info/namespace_packages.txt
odoo10_addon_crm_sale_marketing-10.0.1.0.0.dist-info/top_level.txt
